Metadata-Version: 1.1
Name: rmcolor
Version: 0.0.1b0
Summary: Imprime texto a color en la consola
Home-page: UNKNOWN
Author: Raudin Moreno
Author-email: raudin247@gmail.com
License: Copyright 2018 rcolor
